{
  "type": "object",
  "properties": {
    "app": {
      "type": "string",
      "deprecated": true
    },
    "version": {
      "type": "string"
    },
    "date": {
      "type": "string",
      "format": "date-time"
    },
    "type": {
      "type": "string"
    },
    "ledger": {
      "type": "string",
      "deprecated": true
    },
    "payload": {
      "type": "object",
      "additionalProperties": true
    }
  },
  "required": [
    "date",
    "version",
    "type",
    "payload"
  ]
}