{
  "inputs": [
    {
      "inputFile": "./base.yaml"
    },
    {
      "inputURL": "https://github.com/formancehq/stack/releases/download/ee%2Fauth%2FAUTH_VERSION/openapi.yaml",
      "pathModification":{
        "prepend": "/api/auth"
      },
      "dispute": {
        "prefix": "auth"
      }
    },
    {
      "inputURL": "https://github.com/formancehq/ledger/releases/download/LEDGER_VERSION/openapi.yaml",
      "pathModification":{
        "prepend": "/api/ledger"
      },
      "dispute": {
        "prefix": "ledger"
      }
    },
    {
      "inputURL": "https://github.com/formancehq/stack/releases/download/components%2Fpayments%2FPAYMENTS_VERSION/openapi.yaml",
      "pathModification":{
        "prepend": "/api/payments"
      },
      "dispute": {
        "prefix": "payments"
      }
    },
    {
      "inputURL": "https://github.com/formancehq/stack/releases/download/ee%2Fsearch%2FSEARCH_VERSION/openapi.yaml",
      "pathModification":{
        "prepend": "/api/search"
      },
      "dispute": {
        "prefix": "search"
      }
    },
    {
      "inputURL": "https://github.com/formancehq/stack/releases/download/ee%2Fwebhooks%2FWEBHOOKS_VERSION/openapi.yaml",
      "pathModification":{
        "prepend": "/api/webhooks"
      },
      "operationSelection": {
        "excludeTags": ["Health"]
      },
      "dispute": {
        "prefix": "webhooks"
      }
    },
    {
      "inputURL": "https://github.com/formancehq/stack/releases/download/ee%2Fwallets%2FWALLETS_VERSION/openapi.yaml",
      "pathModification":{
        "prepend": "/api/wallets"
      },
      "operationSelection": {
        "excludeTags": ["Health"]
      },
      "dispute": {
        "prefix": "wallets"
      }
    },
    {
      "inputURL": "https://github.com/formancehq/stack/releases/download/ee%2Forchestration%2FORCHESTRATION_VERSION/openapi.yaml",
      "pathModification":{
        "prepend": "/api/orchestration"
      },
      "operationSelection": {
        "excludeTags": ["Health"]
      },
      "dispute": {
        "prefix": "orchestration"
      }
    },
    {
      "inputURL": "https://github.com/formancehq/stack/releases/download/ee%2Freconciliation%2FRECONCILIATION_VERSION/openapi.yaml",
      "pathModification":{
        "prepend": "/api/reconciliation"
      },
      "operationSelection": {
        "excludeTags": ["Health"]
      },
      "dispute": {
        "prefix": "reconciliation"
      }
    }
  ],
  "output": "OUTPUT_FILE"
}
